kongming/__init__.py
kongming/cli.py
kongming/kongming.py
kongming/main.py
kongming-0.1.2.dist-info/AUTHORS.rst
kongming-0.1.2.dist-info/LICENSE
kongming-0.1.2.dist-info/METADATA
kongming-0.1.2.dist-info/WHEEL
kongming-0.1.2.dist-info/entry_points.txt
kongming-0.1.2.dist-info/top_level.txt
kongming-0.1.2.dist-info/RECORD
