Metadata-Version: 2.1
Name: kongming
Version: 0.1.2
Summary: Collect arrows from parsing results.
Home-page: https://github.com/jun-harashima/kongming
Author: Jun Harashima
Author-email: j.harashima@gmail.com
License: MIT license
Keywords: kongming
Platform: UNKNOWN
Classifier: Development Status :: 2 - Pre-Alpha
Classifier: Intended Audience :: Developers
Classifier: License :: OSI Approved :: MIT License
Classifier: Natural Language :: English
Classifier: Programming Language :: Python :: 3
Classifier: Programming Language :: Python :: 3.5
Classifier: Programming Language :: Python :: 3.6
Classifier: Programming Language :: Python :: 3.7
Classifier: Programming Language :: Python :: 3.8
Requires-Python: >=3.5
Requires-Dist: Click (>=7.0)
